gobe/__init__.py
gobe-0.1.0.dist-info/licenses/LICENSE
gobe-0.1.0.dist-info/METADATA
gobe-0.1.0.dist-info/WHEEL
gobe-0.1.0.dist-info/entry_points.txt
gobe-0.1.0.dist-info/top_level.txt
gobe-0.1.0.dist-info/RECORD
