Metadata-Version: 2.4
Name: gobe
Version: 0.1.0
Summary: Modern Python Web Framework with Unity Integration
Home-page: https://github.com/gobe-team/gobe
Author: Gobe Team
Author-email: Gobe Team <contact@gobe.dev>
Maintainer-email: Gobe Team <contact@gobe.dev>
License: MIT
Project-URL: Homepage, https://gobe.dev
Project-URL: Documentation, https://gobe.dev/docs
Project-URL: Repository, https://github.com/gobe-team/gobe-framework
Project-URL: Bug Tracker, https://github.com/gobe-team/gobe-framework/issues
Project-URL: Changelog, https://github.com/gobe-team/gobe-framework/blob/main/CHANGELOG.md
Keywords: web,framework,django,flask,fastapi,unity,gamedev,rest,api,graphql,websocket
Classifier: Development Status :: 3 - Alpha
Classifier: Intended Audience :: Developers
Classifier: License :: OSI Approved :: MIT License
Classifier: Operating System :: OS Independent
Classifier: Programming Language :: Python :: 3
Classifier: Programming Language :: Python :: 3.8
Classifier: Programming Language :: Python :: 3.9
Classifier: Programming Language :: Python :: 3.10
Classifier: Programming Language :: Python :: 3.11
Classifier: Framework :: AsyncIO
Classifier: Topic :: Internet :: WWW/HTTP :: Dynamic Content
Classifier: Topic :: Internet :: WWW/HTTP :: WSGI :: Application
Classifier: Topic :: Software Development :: Libraries :: Application Frameworks
Classifier: Topic :: Software Development :: Libraries :: Python Modules
Classifier: Topic :: Games/Entertainment
Requires-Python: >=3.8
License-File: LICENSE
Requires-Dist: click>=8.0
Requires-Dist: jinja2>=3.0
Requires-Dist: watchdog>=2.0
Provides-Extra: dev
Requires-Dist: pytest>=6.0; extra == "dev"
Requires-Dist: pytest-cov>=2.0; extra == "dev"
Requires-Dist: black>=21.0; extra == "dev"
Requires-Dist: flake8>=3.8; extra == "dev"
Requires-Dist: mypy>=0.910; extra == "dev"
Requires-Dist: pre-commit>=2.0; extra == "dev"
Requires-Dist: isort>=5.0; extra == "dev"
Provides-Extra: docs
Requires-Dist: sphinx>=4.0; extra == "docs"
Requires-Dist: sphinx-rtd-theme>=1.0; extra == "docs"
Requires-Dist: sphinxcontrib-napoleon>=0.7; extra == "docs"
Requires-Dist: myst-parser>=0.18; extra == "docs"
Provides-Extra: websocket
Requires-Dist: websockets>=10.0; extra == "websocket"
Provides-Extra: graphql
Requires-Dist: graphene>=3.0; extra == "graphql"
Provides-Extra: cache
Requires-Dist: redis>=4.0; extra == "cache"
Requires-Dist: python-memcached>=1.59; extra == "cache"
Provides-Extra: database
Requires-Dist: psycopg2-binary>=2.9; extra == "database"
Requires-Dist: mysqlclient>=2.1; extra == "database"
Provides-Extra: deployment
Requires-Dist: gunicorn>=20.1; extra == "deployment"
Requires-Dist: uvicorn[standard]>=0.15; extra == "deployment"
Provides-Extra: optimization
Requires-Dist: cssmin>=0.2.6; extra == "optimization"
Requires-Dist: jsmin>=3.0.1; extra == "optimization"
Requires-Dist: Pillow>=8.0; extra == "optimization"
Provides-Extra: all
Requires-Dist: websockets>=10.0; extra == "all"
Requires-Dist: graphene>=3.0; extra == "all"
Requires-Dist: redis>=4.0; extra == "all"
Requires-Dist: python-memcached>=1.59; extra == "all"
Requires-Dist: psycopg2-binary>=2.9; extra == "all"
Requires-Dist: mysqlclient>=2.1; extra == "all"
Requires-Dist: gunicorn>=20.1; extra == "all"
Requires-Dist: uvicorn[standard]>=0.15; extra == "all"
Requires-Dist: cssmin>=0.2.6; extra == "all"
Requires-Dist: jsmin>=3.0.1; extra == "all"
Requires-Dist: Pillow>=8.0; extra == "all"
Dynamic: author
Dynamic: home-page
Dynamic: license-file
Dynamic: requires-python
